huaweicloudsdkcampusgo/__init__.py
huaweicloudsdkcampusgo/v2/__init__.py
huaweicloudsdkcampusgo/v2/campusgo_async_client.py
huaweicloudsdkcampusgo/v2/campusgo_client.py
huaweicloudsdkcampusgo/v2/model/__init__.py
huaweicloudsdkcampusgo/v2/model/create_response_body.py
huaweicloudsdkcampusgo/v2/model/create_tasks_request.py
huaweicloudsdkcampusgo/v2/model/create_tasks_request_body.py
huaweicloudsdkcampusgo/v2/model/create_tasks_response.py
huaweicloudsdkcampusgo/v2/model/delete_task_request.py
huaweicloudsdkcampusgo/v2/model/delete_task_response.py
huaweicloudsdkcampusgo/v2/model/list_tasks_details_request.py
huaweicloudsdkcampusgo/v2/model/list_tasks_details_response.py
huaweicloudsdkcampusgo/v2/model/show_task_request.py
huaweicloudsdkcampusgo/v2/model/show_task_response.py
huaweicloudsdkcampusgo/v2/model/task_details.py
huaweicloudsdkcampusgo/v2/model/task_details_error.py
huaweicloudsdkcampusgo/v2/model/task_details_service_title.py
huaweicloudsdkcampusgo/v2/model/task_input.py
huaweicloudsdkcampusgo/v2/model/task_input_data.py
huaweicloudsdkcampusgo/v2/model/task_input_vcn.py
huaweicloudsdkcampusgo/v2/model/task_output.py
huaweicloudsdkcampusgo/v2/model/task_output_dis.py
huaweicloudsdkcampusgo/v2/model/task_output_for_display.py
huaweicloudsdkcampusgo/v2/model/task_output_localpath.py
huaweicloudsdkcampusgo/v2/model/task_output_obs.py
huaweicloudsdkcampusgo/v2/model/task_output_webhook.py
huaweicloudsdkcampusgo/v2/model/task_service_config.py
huaweicloudsdkcampusgo/v2/region/__init__.py
huaweicloudsdkcampusgo/v2/region/campusgo_region.py
huaweicloudsdkcampusgo-3.1.184.dist-info/METADATA
huaweicloudsdkcampusgo-3.1.184.dist-info/WHEEL
huaweicloudsdkcampusgo-3.1.184.dist-info/licenses/LICENSE
huaweicloudsdkcampusgo-3.1.184.dist-info/RECORD
